astrosat/AstroSat.py
astrosat/__init__.py
astrosat/parameters.py
astrosat/plotting.py
astrosat/data/bsc.dat
astrosat-1.0.1.dist-info/METADATA
astrosat-1.0.1.dist-info/WHEEL
astrosat-1.0.1.dist-info/top_level.txt
astrosat-1.0.1.dist-info/RECORD
