Metadata-Version: 2.1
Name: astrosat
Version: 1.0.1
Summary: A tool for forecasting satellite transits in astronomical observations
Home-page: https://github.com/james-m-osborn/astrosat
Author: James Osborn
Author-email: james.osborn@durham.ac.uk, matthew.townson@durham.ac.uk
Classifier: Programming Language :: Python
Classifier: Programming Language :: Python :: 3
